pixelize/__init__.py
pixelize/__main__.py
pixelize/cli.py
pixelize/core.py
pixelize/pixelize.py
pixelize/py.typed
pixelize/utils.py
pixelize-0.0.2.dist-info/LICENSE
pixelize-0.0.2.dist-info/METADATA
pixelize-0.0.2.dist-info/WHEEL
pixelize-0.0.2.dist-info/entry_points.txt
pixelize-0.0.2.dist-info/RECORD
